[
    {
        "image": "https://image.tmdb.org/t/p/original/hAuZ7g6TqDLv5fOqXIPgYRguOkm.jpg",
        "category": "Film Library",
        "title": "Godzilla: Planet of the Monsters (2017)",
        "url": "https://flashstream.cc/pl/QCW2kTSGnw/0-0?e="
    },
    {
        "image": "https://image.tmdb.org/t/p/original/nrMr4ht4CgX4tyseN1uYVHXENJN.jpg",
        "category": "Film Library",
        "title": "Ghost in the Shell Arise - Border 3: Ghost Tears (2014)",
        "url": "https://flashstream.cc/pl/s9gepMzsG_/720?e="
    },
    {
        "image": "https://image.tmdb.org/t/p/original/jUJBKiLv7DkktSzqi1a48tUnWsG.jpg",
        "category": "Film Library",
        "title": "Ajin: Demi-Human - Compel (2015)",
        "url": "https://flashstream.cc/pl/CZydv4NmY0/720?e="
    },
    {
        "image": "https://image.tmdb.org/t/p/original/15z0JrLFFAP39V7WYiOHeZktkPL.jpg",
        "category": "Film Library",
        "title": "Typhoon Noruda (2015)",
        "url": "https://flashstream.cc/pl/TlBYW-697F/720?e="
    },
    {
        "image": "https://image.tmdb.org/t/p/original/9pq1KCvE8gry7QlKszWMgAA6weE.jpg",
        "category": "Film Library",
        "title": "City Hunter: Shinjuku Private Eyes (2019)",
        "url": "https://flashstream.cc/pl/_FUoypcREa/0-0?e="
    }
]