[
    {
        "image": "https://image.tmdb.org/t/p/original/oP568qNH1LLEsoqGiZmf8deTOWc.jpg",
        "category": "Film Library",
        "title": "One Piece Film Z (2012)",
        "url": "https://flashstream.cc/pl/l4uytJ8AHU/0-0?e="
    },
    {
        "image": "https://image.tmdb.org/t/p/original/nBszB6JZkMrwlMRuRtOU14oDDii.jpg",
        "category": "Film Library",
        "title": "Lupin the Third: Steal Napoleon's Dictionary! (1991)",
        "url": "https://flashstream.cc/pl/wsorpNhZle/720?e="
    },
    {
        "image": "https://image.tmdb.org/t/p/original/aL5mNV5UgUoQ00qsC6dvwgQcIbA.jpg",
        "category": "Film Library",
        "title": "Genocidal Organ (2017)",
        "url": "https://flashstream.cc/pl/ayrw6BI5ha/720?e="
    },
    {
        "image": "https://image.tmdb.org/t/p/original/AsTlA7dj2ySGY1pzGSD0MoHFhEF.jpg",
        "category": "Film Library",
        "title": "My Hero Academia: World Heroes' Mission (2021)",
        "url": "https://flashstream.cc/pl/GZ9AMZcw_w/720?e="
    },
    {
        "image": "https://image.tmdb.org/t/p/original/ewXQsNeSE2BdM274LifeckTDvTQ.jpg",
        "category": "Film Library",
        "title": "Kick-Heart (2013)",
        "url": "https://flashstream.cc/pl/25msp-EyEL/720?e="
    }
]