[
    {
        "image": "https://media.themoviedb.org/t/p/w220_and_h330_face/yStW1TXF5s7Tbtu9KjIZEaWl6HL.jpg",
        "category": "Film Library",
        "title": "Suzume (2022)",
        "url": "http://103.236.179.86:80/movie/rictms/rictms/2887.mp4"
    },
    {
        "image": "https://media.themoviedb.org/t/p/w220_and_h330_face/qgrk7r1fV4IjuoeiGS5HOhXNdLJ.jpg",
        "category": "Film Library",
        "title": "Weathering with You (2019)",
        "url": "http://103.236.179.86:80/movie/rictms/rictms/650.mp4"
    },
    {
        "image": "https://media.themoviedb.org/t/p/w220_and_h330_face/zstCDlJbuLfZYHNCYygI4syDwrd.jpg",
        "category": "Film Library",
        "title": "Haikyuu!! Movie 3: Genius and Sense (2017)",
        "url": "http://103.236.179.86:80/movie/rictms/rictms/13398.mkv"
    },
    {
        "image": "https://media.themoviedb.org/t/p/w220_and_h330_face/6inkRM1XGBG5vRhclCPWfMenp7N.jpg",
        "category": "Film Library",
        "title": "A Whisker Away (2020)",
        "url": "http://103.236.179.86:80/movie/rictms/rictms/6773.mkv"
    },
    {
        "image": "https://media.themoviedb.org/t/p/w220_and_h330_face/g8rUn0khoYB3G4gPPGTF1Xv9Olu.jpg",
        "category": "Film Library",
        "title": "Mars Express (2023)",
        "url": "http://103.236.179.86:80/movie/rictms/rictms/7971.mp4"
    }
]